pyIsotherm/.gitignore
pyIsotherm/Estimation.py
pyIsotherm/Isotherm.py
pyIsotherm/Load.py
pyIsotherm/Models.py
pyIsotherm/Particle.py
pyIsotherm/Result.py
pyIsotherm/__init__.py
pyIsotherm/.idea/.gitignore
pyIsotherm/.idea/misc.xml
pyIsotherm/.idea/modules.xml
pyIsotherm/.idea/other.xml
pyIsotherm/.idea/pyMono.iml
pyIsotherm/.idea/vcs.xml
pyIsotherm/.idea/workspace.xml
pyIsotherm/.idea/inspectionProfiles/Project_Default.xml
pyIsotherm/.idea/inspectionProfiles/profiles_settings.xml
pyisotherm-0.0.2.dist-info/METADATA
pyisotherm-0.0.2.dist-info/WHEEL
pyisotherm-0.0.2.dist-info/licenses/LICENSE
pyisotherm-0.0.2.dist-info/RECORD
