Metadata-Version: 2.3
Name: pyIsotherm
Version: 0.0.2
Summary: Parameter estimation of monocomponent-isotherms
Author-email: Pedro Henrique Teodoro de Mendonça <pedrohenrique_teodoromendonca@hotmail.com>, Evandro Alves Nakajima <enakajima@utfpr.edu.br>
Maintainer-email: Pedro Henrique Teodoro de Mendonça <pedrohenrique_teodoromendonca@hotmail.com>, Evandro Alves Nakajima <enakajima@utfpr.edu.br>
License:                     GNU GENERAL PUBLIC LICENSE
License-File: LICENSE
Keywords: Isotherm,Monocomponent,PSO
Classifier: Development Status :: 4 - Beta
Classifier: Programming Language :: Python
Requires-Python: >=3.8
Requires-Dist: matplotlib
Requires-Dist: numpy
Requires-Dist: pandas
Requires-Dist: scipy
